.gitignore
.pylintrc
.readthedocs.yml
CODE_OF_CONDUCT.md
LICENSE
README.rst
adafruit_lsm6ds.py
register_map.json
requirements.txt
setup.py
.github/workflows/build.yml
.github/workflows/release.yml
adafruit_circuitpython_lsm6dsox.egg-info/PKG-INFO
adafruit_circuitpython_lsm6dsox.egg-info/SOURCES.txt
adafruit_circuitpython_lsm6dsox.egg-info/dependency_links.txt
adafruit_circuitpython_lsm6dsox.egg-info/requires.txt
adafruit_circuitpython_lsm6dsox.egg-info/top_level.txt
docs/api.rst
docs/conf.py
docs/examples.rst
docs/index.rst
docs/_static/favicon.ico
examples/ism330dhct_simpletest.py
examples/lsm6ds33_simpletest.py
examples/lsm6ds_full_test.py
examples/lsm6ds_rate_test.py
examples/lsm6dsox_simpletest.py