Metadata-Version: 2.1
Name: adafruit-circuitpython-lsm6dsox
Version: 2.0.0
Summary: CircuitPython library for the ST LSM6DSOX 6-axis Accelerometer and Gyro
Home-page: https://github.com/adafruit/Adafruit_CircuitPython_LSM6DSOX
Author: Adafruit Industries
Author-email: circuitpython@adafruit.com
License: MIT
Keywords: adafruit blinka circuitpython micropython lsm6dsox imu gyro gyroscope inemo accelerometer
Platform: UNKNOWN
Classifier: Development Status :: 3 - Alpha
Classifier: Intended Audience :: Developers
Classifier: Topic :: Software Development :: Libraries
Classifier: Topic :: System :: Hardware
Classifier: License :: OSI Approved :: MIT License
Classifier: Programming Language :: Python :: 3
Classifier: Programming Language :: Python :: 3.4
Classifier: Programming Language :: Python :: 3.5
